terra_ui_components/README.md
terra_ui_components/__init__.py
terra_ui_components/base.py
terra_ui_components/accordion/__init__.py
terra_ui_components/accordion/accordion.py
terra_ui_components/browse_variables/__init__.py
terra_ui_components/browse_variables/browse_variables.py
terra_ui_components/data_access/__init__.py
terra_ui_components/data_access/data_access.py
terra_ui_components/data_rods/__init__.py
terra_ui_components/data_rods/data_rods.py
terra_ui_components/data_subsetter/__init__.py
terra_ui_components/data_subsetter/data_subsetter.py
terra_ui_components/data_subsetter_history/__init__.py
terra_ui_components/data_subsetter_history/data_subsetter_history.py
terra_ui_components/date_picker/__init__.py
terra_ui_components/date_picker/date_picker.py
terra_ui_components/date_range_slider/__init__.py
terra_ui_components/date_range_slider/date_range_slider.py
terra_ui_components/dialog/__init__.py
terra_ui_components/dialog/dialog.py
terra_ui_components/earthdata_login/__init__.py
terra_ui_components/earthdata_login/earthdata_login.py
terra_ui_components/input/__init__.py
terra_ui_components/input/input.py
terra_ui_components/login/__init__.py
terra_ui_components/login/login.py
terra_ui_components/plot_toolbar/__init__.py
terra_ui_components/plot_toolbar/plot_toolbar.py
terra_ui_components/slider/__init__.py
terra_ui_components/slider/slider.py
terra_ui_components/time_average_map/__init__.py
terra_ui_components/time_average_map/time_average_map.py
terra_ui_components/time_series/__init__.py
terra_ui_components/time_series/time_series.py
terra_ui_components/variable_keyword_search/__init__.py
terra_ui_components/variable_keyword_search/variable_keyword_search.py
terra_ui_components-0.0.138.dist-info/METADATA
terra_ui_components-0.0.138.dist-info/WHEEL
terra_ui_components-0.0.138.dist-info/licenses/LICENSE.md
terra_ui_components-0.0.138.dist-info/RECORD
