Metadata-Version: 2.4
Name: terra_ui_components
Version: 0.0.138
Summary: NASA Terra UI Components Library
License-File: LICENSE.md
Requires-Python: >=3.8
Requires-Dist: anywidget>=0.9
Provides-Extra: dev
Requires-Dist: jupyterlab; extra == 'dev'
Requires-Dist: watchfiles; extra == 'dev'
